agentenv/__init__.py
agentenv-0.0.1.dist-info/METADATA
agentenv-0.0.1.dist-info/WHEEL
agentenv-0.0.1.dist-info/top_level.txt
agentenv-0.0.1.dist-info/RECORD
